subsfinder/__init__.py
subsfinder/run.py
subsfinder/run_gevent.py
subsfinder/run_thread.py
subsfinder/subfinder_gevent.py
subsfinder/subfinder_thread.py
subsfinder/subsfinder.py
subsfinder/utils.py
subsfinder/subsearcher/__init__.py
subsfinder/subsearcher/exceptions.py
subsfinder/subsearcher/shooter.py
subsfinder/subsearcher/subhd.py
subsfinder/subsearcher/subsearcher.py
subsfinder/subsearcher/zimuku.py
subsfinder/tools/__init__.py
subsfinder/tools/compressed_file.py
subsfinder/tools/unrar.exe
SubsFinder-3.0.3.dist-info/LICENSE
SubsFinder-3.0.3.dist-info/METADATA
SubsFinder-3.0.3.dist-info/WHEEL
SubsFinder-3.0.3.dist-info/entry_points.txt
SubsFinder-3.0.3.dist-info/top_level.txt
SubsFinder-3.0.3.dist-info/RECORD
