Metadata-Version: 2.1
Name: SubsFinder
Version: 3.0.3
Summary: subsfinder -- a general finder for subtitles
Home-page: https://github.com/wflc/subsfinder/
Author: wflc
Author-email: wflc@163.com
License: MIT
Keywords: subtitle,subsfinder,sub,subtitle finder,shooter,zimuku
Platform: UNKNOWN
Requires-Python: >=3
License-File: LICENSE
Requires-Dist: requests
Requires-Dist: lxml
Requires-Dist: bs4
Requires-Dist: gevent
Requires-Dist: rarfile
Requires-Dist: six
